setup.py
alpinonaf/__init__.py
alpinonaf/__main__.py
alpinonaf/alpino_dependency.py
alpinonaf/convert_penn_to_kaf.py
alpinonaf/morph_syn_parser.py
alpinonaf/tree.py
alpinonaf.egg-info/PKG-INFO
alpinonaf.egg-info/SOURCES.txt
alpinonaf.egg-info/dependency_links.txt
alpinonaf.egg-info/requires.txt
alpinonaf.egg-info/top_level.txt