Metadata-Version: 1.0
Name: alpinonaf
Version: 0.4
Summary: NAF Wrapper around the Alpino parser
Home-page: https://github.com/cltl/alpinonaf
Author: Ruben Izquierdo
Author-email: rubensanvi@gmail.com
License: UNKNOWN
Platform: UNKNOWN
